intake_markdown/__init__.py
intake_markdown/intake_markdown.py
intake_markdown-0.0.2.dist-info/LICENSE
intake_markdown-0.0.2.dist-info/METADATA
intake_markdown-0.0.2.dist-info/WHEEL
intake_markdown-0.0.2.dist-info/entry_points.txt
intake_markdown-0.0.2.dist-info/top_level.txt
intake_markdown-0.0.2.dist-info/RECORD
