Metadata-Version: 2.1
Name: intake-markdown
Version: 0.0.2
Summary: A intake driver for use with markdown files
Author-email: James Morley <jammor966@gmail.com>
License: Copyright (c) 2017, Anaconda, Inc.
Classifier: Programming Language :: Python :: 3
Classifier: License :: OSI Approved :: BSD License
Classifier: Operating System :: OS Independent
Requires-Python: >=3.7
License-File: LICENSE
Requires-Dist: intake
Requires-Dist: ipython
Requires-Dist: requests
Requires-Dist: aiohttp
Requires-Dist: Pygments
Requires-Dist: beautifulsoup4
Requires-Dist: markdown
